EUVpy/__init__.py
EUVpy/NEUVAC/__init__.py
EUVpy/NEUVAC/neuvac.py
EUVpy/data/__init__.py
EUVpy/data/neuvac_euv_2022-01-01_to_2022-12-31.txt
EUVpy/data/neuvac_table.txt
EUVpy/data/neuvac_table_stan_bands.txt
EUVpy/empiricalModels/__init__.py
EUVpy/empiricalModels/models/__init__.py
EUVpy/empiricalModels/models/EUVAC/__init__.py
EUVpy/empiricalModels/models/EUVAC/euvac.py
EUVpy/empiricalModels/models/HEUVAC/__init__.py
EUVpy/empiricalModels/models/HEUVAC/heuvac.py
EUVpy/empiricalModels/models/SOLOMON/__init__.py
EUVpy/empiricalModels/models/SOLOMON/solomon.py
EUVpy/experiments/analyzeIrradiance.py
EUVpy/experiments/fitNeuvac.py
EUVpy/experiments/uncIrradiance.py
EUVpy/tools/__init__.py
EUVpy/tools/ensemble.py
EUVpy/tools/processIndices.py
EUVpy/tools/processIrradiances.py
EUVpy/tools/spectralAnalysis.py
EUVpy/tools/toolbox.py
EUVpy/tools/EUV/__init__.py
EUVpy/tools/EUV/fism2_process.py
euvpy-1.0.0.dist-info/licenses/LICENSE
euvpy-1.0.0.dist-info/METADATA
euvpy-1.0.0.dist-info/WHEEL
euvpy-1.0.0.dist-info/top_level.txt
euvpy-1.0.0.dist-info/RECORD
