Metadata-Version: 2.4
Name: EUVpy
Version: 1.0.0
Summary: A Python package for modeling Solar EUV irradiance.
Author: Daniel A. Brandt
Author-email: daabrand@mtu.edu
Classifier: Development Status :: 3 - Alpha
Classifier: Intended Audience :: Developers
Classifier: Topic :: Software Development :: Build Tools
Classifier: License :: OSI Approved :: MIT License
Classifier: Programming Language :: Python :: 3
Classifier: Programming Language :: Python :: 3.7
Classifier: Programming Language :: Python :: 3.8
Classifier: Programming Language :: Python :: 3.9
Classifier: Programming Language :: Python :: 3.10
Classifier: Programming Language :: Python :: 3 :: Only
Requires-Python: >=3.7, <4
License-File: LICENSE
Requires-Dist: csaps
Requires-Dist: matplotlib
Requires-Dist: netCDF4
Requires-Dist: numpy
Requires-Dist: pandas
Requires-Dist: pygam
Requires-Dist: scikit_learn
Requires-Dist: scipy
Requires-Dist: seaborn
Requires-Dist: tqdm
Requires-Dist: sphinx
Requires-Dist: myst_parser
Requires-Dist: sphinx_rtd_theme
Requires-Dist: pytest
Requires-Dist: pyqt5
Requires-Dist: jupyterlab
Provides-Extra: dev
Requires-Dist: PyQt5; extra == "dev"
Dynamic: author
Dynamic: author-email
Dynamic: classifier
Dynamic: description
Dynamic: description-content-type
Dynamic: license-file
Dynamic: provides-extra
Dynamic: requires-dist
Dynamic: requires-python
Dynamic: summary
